odoo9_addon_stock_quant_reserved_qty_uom-9.0.1.0.0-py2.7-nspkg.pth
odoo9_addon_stock_quant_reserved_qty_uom-9.0.1.0.0.dist-info/top_level.txt
odoo9_addon_stock_quant_reserved_qty_uom-9.0.1.0.0.dist-info/WHEEL
odoo9_addon_stock_quant_reserved_qty_uom-9.0.1.0.0.dist-info/RECORD
odoo9_addon_stock_quant_reserved_qty_uom-9.0.1.0.0.dist-info/metadata.json
odoo9_addon_stock_quant_reserved_qty_uom-9.0.1.0.0.dist-info/DESCRIPTION.rst
odoo9_addon_stock_quant_reserved_qty_uom-9.0.1.0.0.dist-info/METADATA
odoo9_addon_stock_quant_reserved_qty_uom-9.0.1.0.0.dist-info/namespace_packages.txt
odoo_addons/stock_quant_reserved_qty_uom/__openerp__.py
odoo_addons/stock_quant_reserved_qty_uom/__init__.py
odoo_addons/stock_quant_reserved_qty_uom/README.rst
odoo_addons/stock_quant_reserved_qty_uom/models/stock_quant.py
odoo_addons/stock_quant_reserved_qty_uom/models/__init__.py
odoo_addons/stock_quant_reserved_qty_uom/views/stock_quant_view.xml
odoo_addons/stock_quant_reserved_qty_uom/tests/test_stock_quant_reserved_qty_uom.py
odoo_addons/stock_quant_reserved_qty_uom/tests/__init__.py
odoo_addons/stock_quant_reserved_qty_uom/static/description/icon.png
